hullermeier.py
hullermeier-0.1.2.dist-info/LICENSE
hullermeier-0.1.2.dist-info/METADATA
hullermeier-0.1.2.dist-info/WHEEL
hullermeier-0.1.2.dist-info/RECORD
